tdads/PH_utils.py
tdads/__init__.py
tdads/diagram_utils.py
tdads/distance.py
tdads/inference.py
tdads/kernel.py
tdads/machine_learning.py
tdads/tdads.py
tdads-0.1.3.dist-info/LICENSE
tdads-0.1.3.dist-info/METADATA
tdads-0.1.3.dist-info/WHEEL
tdads-0.1.3.dist-info/RECORD
